Metadata-Version: 2.1
Name: speechinput
Version: 0.0.1
Summary: Speech input provides a simple function to get an input from speech. It works like the buildin input function.
Home-page: https://github.com/VicoShortman/speech-input
Author: Vico Shortman
Author-email: vico.shortman@gmail.com
License: MIT
Keywords: speechrecognition speech input
Platform: UNKNOWN
Classifier: Development Status :: 5 - Production/Stable
Classifier: Intended Audience :: Developers
Classifier: Operating System :: OS Independent
Classifier: License :: OSI Approved :: MIT License
Classifier: Programming Language :: Python :: 3
License-File: LICENCE.txt
